pyap_beauhurst/__init__.py
pyap_beauhurst/address.py
pyap_beauhurst/api.py
pyap_beauhurst/exceptions.py
pyap_beauhurst/parser.py
pyap_beauhurst/py.typed
pyap_beauhurst/utils.py
pyap_beauhurst/source_CA/__init__.py
pyap_beauhurst/source_CA/data.py
pyap_beauhurst/source_GB/__init__.py
pyap_beauhurst/source_GB/data.py
pyap_beauhurst/source_US/__init__.py
pyap_beauhurst/source_US/data.py
pyap_beauhurst-0.5.0.dist-info/METADATA
pyap_beauhurst-0.5.0.dist-info/WHEEL
pyap_beauhurst-0.5.0.dist-info/licenses/AUTHORS.rst
pyap_beauhurst-0.5.0.dist-info/RECORD
