Metadata-Version: 2.4
Name: pyap-beauhurst
Version: 0.5.0
Summary: Pyap is an MIT Licensed text processing library, written in Python, for detecting and parsing addresses. Currently it supports USA, Canadian and British addresses. This is a fork maintained by Beauhurst.
Author-email: Vladimir Goncharov <vladimarius@gmail.com>, Beauhurst <dev@beauhurst.com>
License-Expression: MIT
License-File: AUTHORS.rst
Classifier: Operating System :: OS Independent
Classifier: Programming Language :: Python :: 3
Classifier: Programming Language :: Python :: 3 :: Only
Classifier: Programming Language :: Python :: 3.11
Classifier: Programming Language :: Python :: 3.12
Classifier: Programming Language :: Python :: 3.13
Requires-Python: <3.14,>=3.11
Requires-Dist: pydantic>=2
